onepush/__init__.py
onepush/__version__.py
onepush/core.py
onepush/exceptions.py
onepush/providers/__init__.py
onepush/providers/bark.py
onepush/providers/custom.py
onepush/providers/dingtalk.py
onepush/providers/discord.py
onepush/providers/gocqhttp.py
onepush/providers/gotify.py
onepush/providers/lark.py
onepush/providers/ntfy.py
onepush/providers/pushdeer.py
onepush/providers/pushplus.py
onepush/providers/qmsg.py
onepush/providers/serverchan.py
onepush/providers/serverchanturbo.py
onepush/providers/smtp.py
onepush/providers/telegram.py
onepush/providers/wechatworkapp.py
onepush/providers/wechatworkbot.py
onepush-1.7.0.dist-info/LICENSE
onepush-1.7.0.dist-info/METADATA
onepush-1.7.0.dist-info/WHEEL
onepush-1.7.0.dist-info/top_level.txt
onepush-1.7.0.dist-info/RECORD
