Metadata-Version: 2.1
Name: onepush
Version: 1.7.0
Summary: A Python library to send notifications to your iPhone, Discord, Telegram, WeChat, QQ and DingTalk.
Home-page: https://github.com/y1ndan/onepush
Author: y1ndan
Author-email: y1nd4n@outlook.com
License: MIT
Keywords: notify notifier notification push discord telegram wechat qq dingtalk
Platform: UNKNOWN
Classifier: Development Status :: 5 - Production/Stable
Classifier: License :: OSI Approved :: MIT License
Classifier: Operating System :: OS Independent
Classifier: Programming Language :: Python
Classifier: Programming Language :: Python :: 3.6
Classifier: Programming Language :: Python :: 3.7
Classifier: Programming Language :: Python :: 3.8
Classifier: Programming Language :: Python :: 3.9
Classifier: Intended Audience :: Developers
Classifier: Intended Audience :: System Administrators
Classifier: Topic :: System :: Systems Administration
Requires-Python: >=3.6
License-File: LICENSE
Requires-Dist: requests[socks]
Requires-Dist: pycryptodome
